{
  "rows": [
    {
      "rowId": "dw001",
      "season": "2024SS",
      "waveId": "w1",
      "waveName": "W1 春季首发",
      "seriesId": "s001",
      "seriesName": "Street Wave",
      "weekLabel": "第 1 周",
      "dropDate": "2024-03-15",
      "skuCode": "SW-001-BLK",
      "itemName": "Street Wave 01",
      "category": "休闲鞋",
      "productRole": "hero",
      "silhouette": "中帮 / 厚底 / 圆头",
      "upperConstruction": "多片拼接鞋面 + 加厚鞋舌",
      "outsoleDirection": "外扩厚底 + 前掌弯折槽",
      "materialFocus": "反绒皮 + 网眼布",
      "colorDirection": "黑白基底 + 荧光点缀",
      "longLeadMaterial": [
        "TPU 支撑片"
      ],
      "materialLockDate": "2024-02-02",
      "toolingStartDate": "2024-01-22",
      "toolingTrialDate": "2024-02-16",
      "toolingFreezeDate": "2024-02-28",
      "techPackDueDate": "2024-02-05",
      "criticalPathLevel": "critical",
      "referenceAssetIds": [
        "ast001",
        "ast003",
        "ast005"
      ],
      "reviewFocus": "大底体量与帮面比例",
      "phase": "prototype_review",
      "owner": "王五",
      "riskLevel": "high",
      "targetCostEstimate": 168,
      "sampleQuotedCost": 182,
      "finalLockedCost": null,
      "techPackStatus": "in_progress",
      "toolingStatus": "in_progress",
      "toolingNotes": "大底侧墙纹路需要再简化。",
      "nextReviewDate": "2024-03-26",
      "source": "manual",
      "sourceId": null,
      "updatedAt": "2024-03-22T00:00:00Z",
      "updatedBy": "开发组",
      "syncStatus": "synced"
    },
    {
      "rowId": "dw002",
      "season": "2024SS",
      "waveId": "w1",
      "waveName": "W1 春季首发",
      "seriesId": "s001",
      "seriesName": "Street Wave",
      "weekLabel": "第 2 周",
      "dropDate": "2024-03-18",
      "skuCode": "SW-002-WHT",
      "itemName": "Street Wave 02",
      "category": "板鞋",
      "productRole": "core",
      "silhouette": "低帮 / 中厚底 / 圆头",
      "upperConstruction": "简化拼接 + 包边鞋口",
      "outsoleDirection": "街头平底纹路",
      "materialFocus": "全粒面皮面",
      "colorDirection": "全白 + 微撞色",
      "longLeadMaterial": [],
      "materialLockDate": null,
      "toolingStartDate": "2024-01-26",
      "toolingTrialDate": "2024-02-20",
      "toolingFreezeDate": "2024-03-01",
      "techPackDueDate": "2024-02-08",
      "criticalPathLevel": "watch",
      "referenceAssetIds": [
        "ast001",
        "ast006"
      ],
      "reviewFocus": "包边细节和鞋口舒适度",
      "phase": "prototype_review",
      "owner": "王五",
      "riskLevel": "medium",
      "targetCostEstimate": 142,
      "sampleQuotedCost": 149,
      "finalLockedCost": null,
      "techPackStatus": "in_progress",
      "toolingStatus": "not_started",
      "toolingNotes": "待鞋口包边确认后开模。",
      "nextReviewDate": "2024-03-25",
      "source": "manual",
      "sourceId": null,
      "updatedAt": "2024-03-22T00:00:00Z",
      "updatedBy": "开发组",
      "syncStatus": "synced"
    },
    {
      "rowId": "dw003",
      "season": "2024SS",
      "waveId": "w1",
      "waveName": "W1 春季首发",
      "seriesId": "s001",
      "seriesName": "Street Wave",
      "weekLabel": "第 3 周",
      "dropDate": "2024-03-25",
      "skuCode": "SW-003-GRN",
      "itemName": "Street Wave 03",
      "category": "休闲鞋",
      "productRole": "core",
      "silhouette": "低帮 / 厚底 / 圆头",
      "upperConstruction": "撞色多片拼接",
      "outsoleDirection": "厚底包边外墙",
      "materialFocus": "反绒皮 + 网眼",
      "colorDirection": "黑绿高对比",
      "longLeadMaterial": [
        "荧光特殊网布"
      ],
      "materialLockDate": "2024-02-10",
      "toolingStartDate": "2024-01-30",
      "toolingTrialDate": "2024-02-24",
      "toolingFreezeDate": "2024-03-05",
      "techPackDueDate": "2024-02-09",
      "criticalPathLevel": "watch",
      "referenceAssetIds": [
        "ast005",
        "ast006"
      ],
      "reviewFocus": "荧光色比例与市场接受度",
      "phase": "prototype_review",
      "owner": "王五",
      "riskLevel": "medium",
      "targetCostEstimate": 158,
      "sampleQuotedCost": 167,
      "finalLockedCost": null,
      "techPackStatus": "in_progress",
      "toolingStatus": "in_progress",
      "toolingNotes": "侧墙撞色面需要控制面积。",
      "nextReviewDate": "2024-03-27",
      "source": "manual",
      "sourceId": null,
      "updatedAt": "2024-03-22T00:00:00Z",
      "updatedBy": "开发组",
      "syncStatus": "synced"
    },
    {
      "rowId": "dw004",
      "season": "2024SS",
      "waveId": "w1",
      "waveName": "W1 春季首发",
      "seriesId": "s002",
      "seriesName": "Urban Trail",
      "weekLabel": "第 1 周",
      "dropDate": "2024-03-20",
      "skuCode": "UT-001-GRY",
      "itemName": "Urban Trail 01",
      "category": "户外鞋",
      "productRole": "hero",
      "silhouette": "低帮 / 流线 / 圆头",
      "upperConstruction": "防水袜套 + 贴膜分区",
      "outsoleDirection": "全地形齿纹 + 前翘滚动感",
      "materialFocus": "防水面料 + 耐磨橡胶",
      "colorDirection": "灰黑机能色",
      "longLeadMaterial": [
        "防水膜面料",
        "Vibram 外底"
      ],
      "materialLockDate": "2024-01-25",
      "toolingStartDate": "2024-01-15",
      "toolingTrialDate": "2024-02-08",
      "toolingFreezeDate": "2024-02-22",
      "techPackDueDate": "2024-01-26",
      "criticalPathLevel": "critical",
      "referenceAssetIds": [
        "ast008",
        "ast002",
        "ast007"
      ],
      "reviewFocus": "鞋头包覆和防水结构",
      "phase": "sample_review",
      "owner": "张三",
      "riskLevel": "low",
      "targetCostEstimate": 248,
      "sampleQuotedCost": 255,
      "finalLockedCost": null,
      "techPackStatus": "completed",
      "toolingStatus": "in_progress",
      "toolingNotes": "鞋头防撞模具寿命需要验证。",
      "nextReviewDate": null,
      "source": "manual",
      "sourceId": null,
      "updatedAt": "2024-03-22T00:00:00Z",
      "updatedBy": "开发组",
      "syncStatus": "synced"
    },
    {
      "rowId": "dw005",
      "season": "2024SS",
      "waveId": "w1",
      "waveName": "W1 春季首发",
      "seriesId": "s002",
      "seriesName": "Urban Trail",
      "weekLabel": "第 2 周",
      "dropDate": "2024-03-27",
      "skuCode": "UT-002-BLK",
      "itemName": "Urban Trail 02",
      "category": "户外鞋",
      "productRole": "core",
      "silhouette": "低帮 / 机能中底 / 圆头",
      "upperConstruction": "通勤向简化鞋面",
      "outsoleDirection": "轻量防滑大底",
      "materialFocus": "防水布 + 橡胶底",
      "colorDirection": "全黑商务机能",
      "longLeadMaterial": [
        "防水布"
      ],
      "materialLockDate": "2024-02-01",
      "toolingStartDate": "2024-01-20",
      "toolingTrialDate": "2024-02-14",
      "toolingFreezeDate": "2024-02-26",
      "techPackDueDate": "2024-01-30",
      "criticalPathLevel": "watch",
      "referenceAssetIds": [
        "ast007",
        "ast015"
      ],
      "reviewFocus": "城市通勤感和户外感平衡",
      "phase": "prototype_review",
      "owner": "张三",
      "riskLevel": "medium",
      "targetCostEstimate": 215,
      "sampleQuotedCost": 228,
      "finalLockedCost": null,
      "techPackStatus": "completed",
      "toolingStatus": "in_progress",
      "toolingNotes": "前掌防滑纹深度待确认。",
      "nextReviewDate": "2024-03-24",
      "source": "manual",
      "sourceId": null,
      "updatedAt": "2024-03-22T00:00:00Z",
      "updatedBy": "开发组",
      "syncStatus": "synced"
    },
    {
      "rowId": "dw006",
      "season": "2024SS",
      "waveId": "w1",
      "waveName": "W1 春季首发",
      "seriesId": "s002",
      "seriesName": "Urban Trail",
      "weekLabel": "第 3 周",
      "dropDate": "2024-04-02",
      "skuCode": "UT-003-OLV",
      "itemName": "Urban Trail 03",
      "category": "徒步鞋",
      "productRole": "filler",
      "silhouette": "低帮 / 稍厚底 / 圆头",
      "upperConstruction": "功能贴片 + 快速系带",
      "outsoleDirection": "多向防滑纹路",
      "materialFocus": "尼龙 + 橡胶",
      "colorDirection": "橄榄绿户外色",
      "longLeadMaterial": [
        "快速系带组件"
      ],
      "materialLockDate": "2024-02-12",
      "toolingStartDate": "2024-02-05",
      "toolingTrialDate": "2024-02-29",
      "toolingFreezeDate": "2024-03-08",
      "techPackDueDate": "2024-02-10",
      "criticalPathLevel": "watch",
      "referenceAssetIds": [
        "ast008",
        "ast015"
      ],
      "reviewFocus": "户外属性是否过强",
      "phase": "concept",
      "owner": "张三",
      "riskLevel": "low",
      "targetCostEstimate": 198,
      "sampleQuotedCost": null,
      "finalLockedCost": null,
      "techPackStatus": "in_progress",
      "toolingStatus": "not_started",
      "toolingNotes": "待确认是否保留在当前波段。",
      "nextReviewDate": "2024-03-31",
      "source": "manual",
      "sourceId": null,
      "updatedAt": "2024-03-22T00:00:00Z",
      "updatedBy": "开发组",
      "syncStatus": "synced"
    },
    {
      "rowId": "dw007",
      "season": "2024SS",
      "waveId": "w2",
      "waveName": "W2 夏季主推",
      "seriesId": "s003",
      "seriesName": "City Classic",
      "weekLabel": "第 1 周",
      "dropDate": "2024-05-10",
      "skuCode": "CC-001-BRN",
      "itemName": "City Classic 01",
      "category": "正装鞋",
      "productRole": "core",
      "silhouette": "尖头 / 低帮 / 修长",
      "upperConstruction": "德比开口 + 简洁包边",
      "outsoleDirection": "皮底 + 橡胶贴片",
      "materialFocus": "头层牛皮",
      "colorDirection": "深棕商务色",
      "longLeadMaterial": [
        "头层牛皮"
      ],
      "materialLockDate": "2024-03-08",
      "toolingStartDate": "2024-02-26",
      "toolingTrialDate": "2024-03-18",
      "toolingFreezeDate": "2024-03-29",
      "techPackDueDate": "2024-03-06",
      "criticalPathLevel": "watch",
      "referenceAssetIds": [
        "ast009",
        "ast004",
        "ast010"
      ],
      "reviewFocus": "楷型舒适度和商务感纯度",
      "phase": "concept",
      "owner": "李四",
      "riskLevel": "medium",
      "targetCostEstimate": 286,
      "sampleQuotedCost": null,
      "finalLockedCost": null,
      "techPackStatus": "not_started",
      "toolingStatus": "not_started",
      "toolingNotes": "商务楷型待优化后再进入工艺包。",
      "nextReviewDate": "2024-03-29",
      "source": "manual",
      "sourceId": null,
      "updatedAt": "2024-03-22T00:00:00Z",
      "updatedBy": "开发组",
      "syncStatus": "synced"
    },
    {
      "rowId": "dw008",
      "season": "2024SS",
      "waveId": "w2",
      "waveName": "W2 夏季主推",
      "seriesId": "s003",
      "seriesName": "City Classic",
      "weekLabel": "第 2 周",
      "dropDate": "2024-05-17",
      "skuCode": "CC-002-BLK",
      "itemName": "City Classic 02",
      "category": "正装鞋",
      "productRole": "core",
      "silhouette": "尖头 / 低帮 / 修长",
      "upperConstruction": "德比开口 + 极简鞋面",
      "outsoleDirection": "薄底稳定片 + 后跟缓震",
      "materialFocus": "头层牛皮 + 真皮内里",
      "colorDirection": "经典黑",
      "longLeadMaterial": [
        "真皮内里"
      ],
      "materialLockDate": "2024-03-12",
      "toolingStartDate": "2024-03-01",
      "toolingTrialDate": "2024-03-22",
      "toolingFreezeDate": "2024-04-03",
      "techPackDueDate": "2024-03-08",
      "criticalPathLevel": "watch",
      "referenceAssetIds": [
        "ast004",
        "ast010"
      ],
      "reviewFocus": "前掌弯折和行走稳定性",
      "phase": "concept",
      "owner": "李四",
      "riskLevel": "medium",
      "targetCostEstimate": 292,
      "sampleQuotedCost": null,
      "finalLockedCost": null,
      "techPackStatus": "not_started",
      "toolingStatus": "not_started",
      "toolingNotes": "等商业评审后进入工艺包。",
      "nextReviewDate": "2024-04-02",
      "source": "manual",
      "sourceId": null,
      "updatedAt": "2024-03-22T00:00:00Z",
      "updatedBy": "开发组",
      "syncStatus": "synced"
    },
    {
      "rowId": "dw009",
      "season": "2024SS",
      "waveId": "w2",
      "waveName": "W2 夏季主推",
      "seriesId": "s003",
      "seriesName": "City Classic",
      "weekLabel": "第 3 周",
      "dropDate": "2024-05-24",
      "skuCode": "CC-003-NVY",
      "itemName": "City Classic 03",
      "category": "乐福鞋",
      "productRole": "filler",
      "silhouette": "低帮 / 修长 / 乐福楷",
      "upperConstruction": "一脚蹬结构 + 柔软鞋口",
      "outsoleDirection": "薄底 + 局部贴片",
      "materialFocus": "小牛皮",
      "colorDirection": "深蓝商务休闲",
      "longLeadMaterial": [],
      "materialLockDate": null,
      "toolingStartDate": "2024-03-08",
      "toolingTrialDate": "2024-03-28",
      "toolingFreezeDate": "2024-04-08",
      "techPackDueDate": "2024-03-12",
      "criticalPathLevel": "normal",
      "referenceAssetIds": [
        "ast009",
        "ast004"
      ],
      "reviewFocus": "鞋口稳定性和通勤适配",
      "phase": "concept",
      "owner": "李四",
      "riskLevel": "medium",
      "targetCostEstimate": 258,
      "sampleQuotedCost": null,
      "finalLockedCost": null,
      "techPackStatus": "not_started",
      "toolingStatus": "not_started",
      "toolingNotes": "等楷型优化结果后再推进。",
      "nextReviewDate": "2024-03-30",
      "source": "manual",
      "sourceId": null,
      "updatedAt": "2024-03-22T00:00:00Z",
      "updatedBy": "开发组",
      "syncStatus": "synced"
    },
    {
      "rowId": "dw010",
      "season": "2024SS",
      "waveId": "w2",
      "waveName": "W2 夏季主推",
      "seriesId": "s004",
      "seriesName": "Comfort Flex",
      "weekLabel": "第 1 周",
      "dropDate": "2024-05-08",
      "skuCode": "CF-001-BLK",
      "itemName": "Comfort Flex 01",
      "category": "乐福鞋",
      "productRole": "filler",
      "silhouette": "低帮 / 宽楷 / 圆头",
      "upperConstruction": "弹力鞋口 + 一脚蹬",
      "outsoleDirection": "轻量 EVA + 前掌弯折槽",
      "materialFocus": "软皮 + 弹力布",
      "colorDirection": "黑色通勤",
      "longLeadMaterial": [
        "EVA 底材",
        "记忆棉鞋垫"
      ],
      "materialLockDate": "2024-03-01",
      "toolingStartDate": "2024-02-20",
      "toolingTrialDate": "2024-03-15",
      "toolingFreezeDate": "2024-03-27",
      "techPackDueDate": "2024-02-28",
      "criticalPathLevel": "critical",
      "referenceAssetIds": [
        "ast011",
        "ast012",
        "ast013"
      ],
      "reviewFocus": "宽楷适配和后跟包裹",
      "phase": "concept",
      "owner": "王五",
      "riskLevel": "high",
      "targetCostEstimate": 152,
      "sampleQuotedCost": null,
      "finalLockedCost": null,
      "techPackStatus": "not_started",
      "toolingStatus": "blocked",
      "toolingNotes": "EVA 底材替代方案未确认。",
      "nextReviewDate": "2024-03-28",
      "source": "manual",
      "sourceId": null,
      "updatedAt": "2024-03-22T00:00:00Z",
      "updatedBy": "开发组",
      "syncStatus": "synced"
    },
    {
      "rowId": "dw011",
      "season": "2024SS",
      "waveId": "w2",
      "waveName": "W2 夏季主推",
      "seriesId": "s004",
      "seriesName": "Comfort Flex",
      "weekLabel": "第 2 周",
      "dropDate": "2024-05-15",
      "skuCode": "CF-002-GRY",
      "itemName": "Comfort Flex 02",
      "category": "乐福鞋",
      "productRole": "filler",
      "silhouette": "低帮 / 宽楷 / 圆头",
      "upperConstruction": "弹力鞋口 + 无压后跟",
      "outsoleDirection": "轻量 EVA 中底",
      "materialFocus": "软皮 + 弹力布",
      "colorDirection": "深灰通勤",
      "longLeadMaterial": [
        "弹力面料"
      ],
      "materialLockDate": "2024-03-05",
      "toolingStartDate": "2024-02-26",
      "toolingTrialDate": "2024-03-20",
      "toolingFreezeDate": "2024-04-01",
      "techPackDueDate": "2024-03-01",
      "criticalPathLevel": "watch",
      "referenceAssetIds": [
        "ast012",
        "ast014"
      ],
      "reviewFocus": "长时间穿着舒适度",
      "phase": "concept",
      "owner": "王五",
      "riskLevel": "high",
      "targetCostEstimate": 148,
      "sampleQuotedCost": null,
      "finalLockedCost": null,
      "techPackStatus": "not_started",
      "toolingStatus": "in_progress",
      "toolingNotes": "前掌弯折槽方案需验证回弹。",
      "nextReviewDate": "2024-04-03",
      "source": "manual",
      "sourceId": null,
      "updatedAt": "2024-03-22T00:00:00Z",
      "updatedBy": "开发组",
      "syncStatus": "synced"
    },
    {
      "rowId": "dw012",
      "season": "2024SS",
      "waveId": "w2",
      "waveName": "W2 夏季主推",
      "seriesId": "s004",
      "seriesName": "Comfort Flex",
      "weekLabel": "第 3 周",
      "dropDate": "2024-05-24",
      "skuCode": "CF-003-CRM",
      "itemName": "Comfort Flex 03",
      "category": "休闲鞋",
      "productRole": "filler",
      "silhouette": "低帮 / 宽楷 / 圆头",
      "upperConstruction": "宽开口 + 软包边",
      "outsoleDirection": "柔软中底 + 稳定外底",
      "materialFocus": "软皮 + 记忆棉",
      "colorDirection": "米白女性向",
      "longLeadMaterial": [
        "记忆棉鞋垫"
      ],
      "materialLockDate": "2024-03-10",
      "toolingStartDate": "2024-03-03",
      "toolingTrialDate": "2024-03-26",
      "toolingFreezeDate": "2024-04-05",
      "techPackDueDate": "2024-03-06",
      "criticalPathLevel": "normal",
      "referenceAssetIds": [
        "ast011",
        "ast014"
      ],
      "reviewFocus": "女性向配色与轻盈感",
      "phase": "concept",
      "owner": "王五",
      "riskLevel": "medium",
      "targetCostEstimate": 146,
      "sampleQuotedCost": null,
      "finalLockedCost": null,
      "techPackStatus": "not_started",
      "toolingStatus": "not_started",
      "toolingNotes": "待女性向配色确认后再推进。",
      "nextReviewDate": "2024-04-05",
      "source": "manual",
      "sourceId": null,
      "updatedAt": "2024-03-22T00:00:00Z",
      "updatedBy": "开发组",
      "syncStatus": "synced"
    }
  ]
}